{"gbDKuQgUx702LNS95RyMNg==":"mbr-1.jpg","04sx91A9OFPVfnHsr0CBug==":"mbr-2.jpg","vx1HCfMmqDU+s7Eui2JRdg==":"mbr-3.jpg","KZ9bLk9AH2ZsJ75m1vIHgA==":"mbr.png","Y3vQ9NrQmNgUekrM4H/8nA==":"mbr-3.jpeg","4jMTBEKvtHt4yLp64yJ7rQ==":"mbr-4.jpg","vlgcUSC18u1mj5K5ihrfAw==":"mbr-7.jpg","tTz86reHysGEwhEcX5uwVA==":"mbr-8.jpg","HPvps2PYs2xvCuXnWbZ9Hw==":"mbr-8.jpeg","KF+Wa3qUz9G/nA/BRqWBHw==":"mbr.jpeg","LsH5lvBYKniR4SADVP1NTQ==":"mbr-9.jpeg","xvEZoRtTpRo8PQiyUW4s5Q==":"mbr-10.jpg","IDI+CXQpTCod/TkNrC3CYQ==":"mbr.jpg","X0NkBDGMu+zd4PYMoLSDwA==":"mbr-5.jpg","wX76oSpNBIHut/EW6vVidQ==":"mbr-1.jpeg","kBWcS24dsvzugKxtOJfDkA==":"mbr-10.jpeg","1M+k9KQr3e0vaqeHdoJ5dQ==":"mbr-1.jpg","JLvC/Pt+1aVzt55sqXn8iA==":"mbr-2.jpg","4I6UtJI1Vw5fVal+WFhEnQ==":"mbr-3.jpg","e7nvDsa7fsSMBsdcQBAeFA==":"mbr-4.jpg","N5bQ73aFKkEv3g7o69tqag==":"descarga-6.jpeg","EU2O9BAXkG+3fiPO+Oj1Yg==":"descarga-5.jpeg","TDSVYnyq4yKVKyfbWspATw==":"descarga-4.jpeg","SB5amzPF/MXewkMJzD7yjQ==":"descarga-3.jpeg","2b5NowEOefPapXkJm4raWA==":"team2.jpg","Ndk17z8Qxi9JEUMR1bQ6ow==":"jeans-casuales-sueltos-de-pierna-ancha-para-mujer-con-mltiples-bolsillos-para-ropa-de-trabajo.jpeg","UVNx/M7eos8P25o2vJ2I/A==":"what-are-the-most-elegant-european-summer-styles-.jpeg","opCYDUewaxRw/1ft9OzJVw==":"descarga-8.jpeg","ZrowQ2uXfP9BkdT46nXUxA==":"descarga-7.jpeg","M6k7Mh4a/EinaD+rSb9YEw==":"diseo-comercial.jpeg","BxvMG1BhE1hB4pCTPLtApA==":"descarga.jpeg","6XIatsrwnV/hKwQmrC9D+w==":"descarga-13.jpeg","jjkZ2bB8iIf+NKWPs7f8Mg==":"descarga-12.jpeg","UZc0I4b5WDgJ7QG8obhd2Q==":"descarga-11.jpeg","1PTg4AcHgshkrpidjX/Qag==":"descarga-9.jpeg","iRbAEYszb7upfW5NRcn95w==":"1-nude-outfit.jpeg","8M8gdijC5PvFMTrgKH8JVw==":"descarga-15.jpeg","lxa3p13Mc1PAMPIfS+jRQA==":"moda.jpeg"}